[
    {
        "action": "jump",
        "x": 451.33333333333377,
        "y": 319.004854368932
    },
    {
        "action": "jump",
        "x": 1199.3333333333323,
        "y": 319.004854368932
    },
    {
        "action": "jump",
        "x": 1630.0000000000048,
        "y": 319.004854368932
    },
    {
        "action": "jump",
        "x": 1924.6666666666754,
        "y": 319.004854368932
    },
    {
        "action": "jump",
        "x": 2395.000000000003,
        "y": 319.004854368932
    },
    {
        "action": "jump",
        "x": 303.99999999999994,
        "y": 319.004854368932
    },
    {
        "action": "jump",
        "x": 1601.666666666671,
        "y": 319.004854368932
    }
]